{
    "en": {
        "login": {
            "title": "Login to Signa",
            "username": "Username",
            "password": "Password",
            "submit": "Login",
            "error": "Wrong username or password"
        },
        "nav": {
            "home": "Home",
            "about": "About Signa",
            "doc": "Documentation",
            "explore": "Explore",
            "blog": "Blog",
            "contact": "Contact"
        }
    },
    "fr": {
        "login": {
            "title": "Se connecter à Signa",
            "username": "Identifiant",
            "password": "Mot de passe",
            "submit": "Envoyer",
            "error": "Identifiant ou mot de passe erroné"
        },
        "nav": {
            "home": "Accueil",
            "about": "À propos de Signa",
            "doc": "Documentation",
            "explore": "Explorer",
            "blog": "Blog",
            "contact": "Contact"
        }
    }
}